{"DN05490062":{"name": "DN05490062"}, "测量控制点":{"name": "测量控制点", "小类别": " 测量控制点类 "}, "工业、农业社会文化设施":{"name": "工业、农业社会文化设施", "小类别": " 工业 农业 科学、文卫 政府、机关、驻地 公共服务设施 港口管理及服务机构设施 航海信号站台 垣榻 其他设施 "}, "居民地及附属设施":{"name": "居民地及附属设施", "小类别": " 独立建筑物 居民区 其他建筑物 "}, "陆地交通":{"name": "陆地交通", "小类别": " 铁路 铁路车站及附属设施 公路 其他道路 附属建筑物 "}, "管线":{"name": "管线", "小类别": " 电力线 通信线 管道 "}, "水域/陆地":{"name": "水域/陆地", "小类别": " 岸线岸 河流 运河、沟渠 湖泊、水库、池塘 水利设施 其他水系要素 一般堤 防洪堤 塘堤 港口、码头 泊位系泊绞缆设施 陆地、海洋岛屿 "}, "海底地貌及底质":{"name": "海底地貌及底质", "小类别": " 深度 海底地质 其他 "}, "礁石、沉船、障碍物":{"name": "礁石、沉船、障碍物", "小类别": " 礁石 沉船 障碍物 捕鱼设施 "}, "水文":{"name": "水文", "小类别": " 内河水文 河流、潮流 强烈水文现象 潮汐、潮信 "}, "陆地地貌及土质":{"name": "陆地地貌及土质", "小类别": " 等高线 地貌高程 雪山地貌 黄土地貌 岩溶地貌 风成地貌 火山地貌 其他地貌 "}, "境界与政区":{"name": "境界与政区", "小类别": " 国界与领海 国内境界 行政区 其他界线 "}, "植被":{"name": "植被", "小类别": " 林地 田地 地类界线 "}, "地磁要素":{"name": "地磁要素", "小类别": " 地磁要素类 "}, "助航设备及航道":{"name": "助航设备及航道", "小类别": " 灯标 灯塔灯桩 活节式灯桩 水中灯桩 塔式立标 格式立标 立标 水中立标 船形灯浮标 灯塔 大型浮标 柱形浮标 杆形浮标 锥形浮标 球形浮标 罐形浮标 桶形浮标 特殊标志 航海雷达 无线电 雾号 航道及相关标示 "}, "海上区域界限":{"name": "海上区域界限", "小类别": " 海上管理区 倾倒区、挖泥区 锚地 海上限制区 近海设施 "}, "航空要素":{"name": "航空要素", "小类别": " 飞机机场 航空障碍物 航空导航 空中区域及界限 航路航线 机场场道及防护措施 "}, "军事区域":{"name": "军事区域", "小类别": " 军事训练区 军事管理区 "}, "标记":{"name": "标记"}, "测量控制点类":{"name": "测量控制点类", "要素编码": "1101"}, "工业":{"name": "工业", "要素编码": "1201"}, "农业":{"name": "农业", "要素编码": "1202"}, "科学、文卫":{"name": "科学、文卫", "要素编码": "1203"}, "政府、机关、驻地":{"name": "政府、机关、驻地", "要素编码": "1204"}, "公共服务设施":{"name": "公共服务设施", "要素编码": "1205"}, "港口管理及服务机构设施":{"name": "港口管理及服务机构设施", "要素编码": "1206"}, "航海信号站台":{"name": "航海信号站台", "要素编码": "1207"}, "垣榻":{"name": "垣榻", "要素编码": "1208"}, "其他设施":{"name": "其他设施", "要素编码": "1209"}, "独立建筑物":{"name": "独立建筑物", "要素编码": "1301"}, "居民区":{"name": "居民区", "要素编码": "1302"}, "其他建筑物":{"name": "其他建筑物", "要素编码": "1303"}, "铁路":{"name": "铁路", "要素编码": "1401"}, "铁路车站及附属设施":{"name": "铁路车站及附属设施", "要素编码": "1402"}, "公路":{"name": "公路", "要素编码": "1403"}, "其他道路":{"name": "其他道路", "要素编码": "1404"}, "附属建筑物":{"name": "附属建筑物", "要素编码": "1405"}, "电力线":{"name": "电力线", "要素编码": "1501"}, "通信线":{"name": "通信线", "要素编码": "1502"}, "管道":{"name": "管道", "要素编码": "1503"}, "岸线岸":{"name": "岸线岸", "要素编码": "1601"}, "河流":{"name": "河流", "要素编码": "1602"}, "运河、沟渠":{"name": "运河、沟渠", "要素编码": "1603"}, "湖泊、水库、池塘":{"name": "湖泊、水库、池塘", "要素编码": "1604"}, "水利设施":{"name": "水利设施", "要素编码": "1605"}, "其他水系要素":{"name": "其他水系要素", "要素编码": "1606"}, "一般堤":{"name": "一般堤", "要素编码": "1607"}, "防洪堤":{"name": "防洪堤", "要素编码": "1608"}, "塘堤":{"name": "塘堤", "要素编码": "1609"}, "港口、码头":{"name": "港口、码头", "要素编码": "1610"}, "泊位系泊绞缆设施":{"name": "泊位系泊绞缆设施", "要素编码": "1611"}, "陆地、海洋岛屿":{"name": "陆地、海洋岛屿", "要素编码": "1612"}, "深度":{"name": "深度", "要素编码": "1701"}, "海底地质":{"name": "海底地质", "要素编码": "1702"}, "其他":{"name": "其他", "要素编码": "1703"}, "礁石":{"name": "礁石", "要素编码": "1801"}, "沉船":{"name": "沉船", "要素编码": "1802"}, "障碍物":{"name": "障碍物", "要素编码": "1803"}, "捕鱼设施":{"name": "捕鱼设施", "要素编码": "1804"}, "内河水文":{"name": "内河水文", "要素编码": "1901"}, "河流、潮流":{"name": "河流、潮流", "要素编码": "1902"}, "强烈水文现象":{"name": "强烈水文现象", "要素编码": "1903"}, "潮汐、潮信":{"name": "潮汐、潮信", "要素编码": "1904"}, "等高线":{"name": "等高线", "要素编码": "2001"}, "地貌高程":{"name": "地貌高程", "要素编码": "2002"}, "雪山地貌":{"name": "雪山地貌", "要素编码": "2003"}, "黄土地貌":{"name": "黄土地貌", "要素编码": "2004"}, "岩溶地貌":{"name": "岩溶地貌", "要素编码": "2005"}, "风成地貌":{"name": "风成地貌", "要素编码": "2006"}, "火山地貌":{"name": "火山地貌", "要素编码": "2007"}, "其他地貌":{"name": "其他地貌", "要素编码": "2008"}, "国界与领海":{"name": "国界与领海", "要素编码": "2101"}, "国内境界":{"name": "国内境界", "要素编码": "2102"}, "行政区":{"name": "行政区", "要素编码": "2103"}, "其他界线":{"name": "其他界线", "要素编码": "2104"}, "林地":{"name": "林地", "要素编码": "2201"}, "田地":{"name": "田地", "要素编码": "2202"}, "地类界线":{"name": "地类界线", "要素编码": "2203"}, "地磁要素类":{"name": "地磁要素类", "要素编码": "2301"}, "灯标":{"name": "灯标", "要素编码": "2401"}, "灯塔灯桩":{"name": "灯塔灯桩", "要素编码": "2402"}, "活节式灯桩":{"name": "活节式灯桩", "要素编码": "2403"}, "水中灯桩":{"name": "水中灯桩", "要素编码": "2404"}, "塔式立标":{"name": "塔式立标", "要素编码": "2405"}, "格式立标":{"name": "格式立标", "要素编码": "2406"}, "立标":{"name": "立标", "要素编码": "2407"}, "水中立标":{"name": "水中立标", "要素编码": "2408"}, "船形灯浮标":{"name": "船形灯浮标", "要素编码": "2409"}, "灯塔":{"name": "灯塔", "要素编码": "2410"}, "大型浮标":{"name": "大型浮标", "要素编码": "2411"}, "柱形浮标":{"name": "柱形浮标", "要素编码": "2412"}, "杆形浮标":{"name": "杆形浮标", "要素编码": "2413"}, "锥形浮标":{"name": "锥形浮标", "要素编码": "2414"}, "球形浮标":{"name": "球形浮标", "要素编码": "2415"}, "罐形浮标":{"name": "罐形浮标", "要素编码": "2416"}, "桶形浮标":{"name": "桶形浮标", "要素编码": "2417"}, "特殊标志":{"name": "特殊标志", "要素编码": "2418"}, "航海雷达":{"name": "航海雷达", "要素编码": "2419"}, "无线电":{"name": "无线电", "要素编码": "2420"}, "雾号":{"name": "雾号", "要素编码": "2421"}, "航道及相关标示":{"name": "航道及相关标示", "要素编码": "2422"}, "海上管理区":{"name": "海上管理区", "要素编码": "2501"}, "倾倒区、挖泥区":{"name": "倾倒区、挖泥区", "要素编码": "2502"}, "锚地":{"name": "锚地", "要素编码": "2503"}, "海上限制区":{"name": "海上限制区", "要素编码": "2504"}, "近海设施":{"name": "近海设施", "要素编码": "2505"}, "飞机机场":{"name": "飞机机场", "要素编码": "2601"}, "航空障碍物":{"name": "航空障碍物", "要素编码": "2602"}, "航空导航":{"name": "航空导航", "要素编码": "2603"}, "空中区域及界限":{"name": "空中区域及界限", "要素编码": "2604"}, "航路航线":{"name": "航路航线", "要素编码": "2605"}, "机场场道及防护措施":{"name": "机场场道及防护措施", "要素编码": "2606"}, "军事训练区":{"name": "军事训练区", "要素编码": "2701"}, "军事管理区":{"name": "军事管理区", "要素编码": "2702"}}